f1/handler.py
f1/listener.py
f1/packets.py
f1_packets-2025.1.1.dist-info/METADATA
f1_packets-2025.1.1.dist-info/WHEEL
f1_packets-2025.1.1.dist-info/licenses/LICENSE
f1_packets-2025.1.1.dist-info/RECORD
