Metadata-Version: 2.4
Name: f1-packets
Version: 2025.1.1
Summary: Python library for the official F1 game UDP telemetry data
Project-URL: repository, https://github.com/P403n1x87/f1-packets
Project-URL: issues, https://github.com/P403n1x87/f1-packets/issues
Author-email: "Gabriele N. Tornetta" <phoenix1987@gmail.com>
License-Expression: MIT
License-File: LICENSE
Classifier: Intended Audience :: Developers
Classifier: Programming Language :: Python :: 3.8
Classifier: Programming Language :: Python :: 3.9
Classifier: Programming Language :: Python :: 3.10
Classifier: Programming Language :: Python :: 3.11
Classifier: Programming Language :: Python :: 3.12
Requires-Python: >=3.8
